LICENSE
README.md
setup.cfg
setup.py
aioirispay/__init__.py
aioirispay/core.py
aioirispay/utils.py
aioirispay.egg-info/PKG-INFO
aioirispay.egg-info/SOURCES.txt
aioirispay.egg-info/dependency_links.txt
aioirispay.egg-info/requires.txt
aioirispay.egg-info/top_level.txt
aioirispay/database/__init__.py
aioirispay/database/db.py
aioirispay/examples/__init__.py
aioirispay/examples/quickstart.py