Metadata-Version: 2.1
Name: aioirispay
Version: 0.1.5
Summary: Python library for automating payments using the iris bot in telegram
Author: immortalbuddha
Author-email: immortalbuddha69@gmail.com
Classifier: Programming Language :: Python :: 3
Classifier: License :: OSI Approved :: MIT License
Classifier: Operating System :: OS Independent
License-File: LICENSE
